{"is_source_file": true, "format": "JavaScript (React JSX)", "description": "This file defines the main React application component 'App' which sets up routing for different pages and demo components within the UI project. It imports core React modules, routing components, layout, page components, demo pages, and context providers.", "external_files": ["./App.css", "./layouts/MainLayout", "./pages/Home", "./pages/NotFound", "./components/ui/ToastProvider", "./pages/demos/AccordionDemo", "./pages/demos/BreadcrumbsDemo", "./pages/demos/ToastDemo", "./pages/demos/FormWizardDemo", "./pages/demos/BentoMenuDemo", "./pages/demos/CarouselDemo", "./pages/demos/ChatbotDemo", "./pages/demos/TestimonialDemo"], "external_methods": ["React", "Routes", "Route", "Navigate"], "published": ["App"], "classes": [], "methods": [{"name": "App()", "description": "React functional component defining application routing and layout.", "scope": "", "scopeKind": ""}], "calls": ["React", "Navigate", "Routes", "Route", "MainLayout", "Home", "AccordionDemoPage", "BentoMenuDemoPage", "BreadcrumbsDemoPage", "CarouselDemoPage", "ChatbotDemoPage", "FormWizardDemoPage", "TestimonialDemoPage", "ToastDemoPage", "NotFound"], "search-terms": ["React", "routing", "MainLayout", "demos", "components/ui/ToastProvider"], "state": 2, "file_id": 9, "knowledge_revision": 85, "git_revision": "7cde72ef2eacedf07ee5fe810770b69ac189c351", "revision_history": [{"25": "70dd5deecc45d8a3f6a67fbd39645f728f86b2a5"}, {"48": "70dd5deecc45d8a3f6a67fbd39645f728f86b2a5"}, {"68": "67887223d79c65828a2794ac753cf1bdb766d51a"}, {"85": "7cde72ef2eacedf07ee5fe810770b69ac189c351"}], "ctags": [{"_type": "tag", "name": "App", "path": "/home/kavia/workspace/code-generation/ui-components-showcase-3705-3714/frontend_react_app/src/App.js", "pattern": "/^function App() {$/", "language": "JavaScript", "kind": "function", "signature": "()"}], "hash": "8d340382470c7abdba36f6f11a806552", "format-version": 4, "code-base-name": "frontend_react_app", "filename": "frontend_react_app/src/App.js"}